uproot3_methods/__init__.py
uproot3_methods/base.py
uproot3_methods/convert.py
uproot3_methods/version.py
uproot3_methods/classes/TGraph.py
uproot3_methods/classes/TGraphAsymmErrors.py
uproot3_methods/classes/TGraphErrors.py
uproot3_methods/classes/TH1.py
uproot3_methods/classes/TH2.py
uproot3_methods/classes/TH3.py
uproot3_methods/classes/THnSparse.py
uproot3_methods/classes/TLorentzVector.py
uproot3_methods/classes/TParameter.py
uproot3_methods/classes/TVector2.py
uproot3_methods/classes/TVector3.py
uproot3_methods/classes/__init__.py
uproot3_methods/common/TVector.py
uproot3_methods/common/__init__.py
uproot3_methods/profiles/__init__.py
uproot3_methods/profiles/cms/__init__.py
uproot3_methods/profiles/cms/nanoaod.py
uproot3_methods-0.10.1.dist-info/AUTHORS
uproot3_methods-0.10.1.dist-info/LICENSE
uproot3_methods-0.10.1.dist-info/METADATA
uproot3_methods-0.10.1.dist-info/WHEEL
uproot3_methods-0.10.1.dist-info/top_level.txt
uproot3_methods-0.10.1.dist-info/RECORD
